graphipy/__init__.py
graphipy/exportnx.py
graphipy/graphipy.py
graphipy/api/__init__.py
graphipy/api/facebook_api.py
graphipy/api/linkedin_api.py
graphipy/api/pinterest_api.py
graphipy/api/reddit_api.py
graphipy/api/tumblr_api.py
graphipy/api/twitter_api.py
graphipy/api/youtube_api.py
graphipy/api/_test/__init__.py
graphipy/api/_test/graph_test.py
graphipy/graph/__init__.py
graphipy/graph/graph_base.py
graphipy/graph/graph_dict.py
graphipy/graph/graph_neo4j.py
graphipy/graph/graph_pandas.py
GraphiPy-0.0.1.dist-info/LICENSE
GraphiPy-0.0.1.dist-info/METADATA
GraphiPy-0.0.1.dist-info/WHEEL
GraphiPy-0.0.1.dist-info/top_level.txt
GraphiPy-0.0.1.dist-info/zip-safe
GraphiPy-0.0.1.dist-info/RECORD
