Metadata-Version: 2.1
Name: GraphiPy
Version: 0.0.1
Summary: A Universal Social Data Extractor
Home-page: https://github.com/shobeir/GraphiPy
Author: Shobeir Fakhraei
Author-email: shobeir@gmail.com
License: MIT
Platform: UNKNOWN
Classifier: License :: OSI Approved :: MIT License
Classifier: Programming Language :: Python
Classifier: Intended Audience :: Developers
Classifier: Operating System :: OS Independent
Requires-Dist: pytumblr (>=0.0.8)
Requires-Dist: httplib2 (>=0.11.3)
Requires-Dist: google-api-python-client (>=1.7.4)
Requires-Dist: google-auth (>=1.5.1)
Requires-Dist: google-auth-oauthlib (>=0.2.0)
Requires-Dist: google-auth-httplib2 (>=0.0.3)
Requires-Dist: oauth2client (>=4.1.3)
Requires-Dist: facebook-sdk (>=3.0.0)
Requires-Dist: pandas (>=0.23.0)
Requires-Dist: py2neo (>=4.1.0)
Requires-Dist: networkX (>=2.2)
